abejaruntime36/__init__.py
abejaruntime36/run.py
abejaruntime36/server_protocol.py
abejaruntime36/version.py
abejaruntime36/converter/__init__.py
abejaruntime36/converter/converter.py
abejaruntime36/entity/__init__.py
abejaruntime36/entity/request.py
abejaruntime36/entity/response.py
abejaruntime36/exception/__init__.py
abejaruntime36/exception/exceptions.py
abejaruntime36/helper/__init__.py
abejaruntime36/helper/json_encoder.py
abejaruntime36/logging/__init__.py
abejaruntime36/logging/logger.py
abejaruntime36/model/__init__.py
abejaruntime36/model/model.py
abejaruntime-1.1.1.dist-info/METADATA
abejaruntime-1.1.1.dist-info/WHEEL
abejaruntime-1.1.1.dist-info/entry_points.txt
abejaruntime-1.1.1.dist-info/top_level.txt
abejaruntime-1.1.1.dist-info/RECORD
