Metadata-Version: 2.1
Name: abejaruntime
Version: 1.1.1
Summary: ABEJA Platform Runtime for Python
Home-page: UNKNOWN
Author: ABEJA Inc.
Author-email: dev@abeja.asia
License: UNKNOWN
Platform: UNKNOWN
Classifier: Development Status :: 5 - Production/Stable
Classifier: Programming Language :: Python :: 3.6
Classifier: Programming Language :: Python :: 3.7
Classifier: Programming Language :: Python :: 3.8
Classifier: Programming Language :: Python :: 3.9
Classifier: Intended Audience :: Developers
Classifier: Operating System :: OS Independent
Classifier: License :: OSI Approved :: Apache Software License
Requires-Python: >=3.6,<4.0
Requires-Dist: numpy
